{
  "project_info": {
    "project_number": "228051656340",
    "project_id": "nexedhub",
    "storage_bucket": "nexedhub.appspot.com"
  },
  "client": [
    {
      "client_info": {
        "mobilesdk_app_id": "1:228051656340:android:0009d12460bd3abf991e81",
        "android_client_info": {
          "package_name": "com.example.nexedhub"
        }
      },
      "oauth_client": [],
      "api_key": [
        {
          "current_key": "AIzaSyCX9TUXOM-J4lrd3biHMdtjumo-8RxCcb4"
        }
      ],
      "services": {
        "appinvite_service": {
          "other_platform_oauth_client": []
        }
      }
    }
  ],
  "configuration_version": "1"
}